README.md
setup.py
coodict/__init__.py
coodict/version.py
coodict.egg-info/PKG-INFO
coodict.egg-info/SOURCES.txt
coodict.egg-info/dependency_links.txt
coodict.egg-info/top_level.txt
tests/__init__.py
tests/speed.py