Metadata-Version: 1.1
Name: coodict
Version: 0.0.6
Summary: A (Scottish) copy-on-write dictionary wrapper class.
Home-page: https://github.com/mrichar1/coodict
Author: Matthew Richardson
Author-email: m.richardson@ed.ac.uk
License: GNU Affero General Public License v3 or later (AGPLv3+)
Keywords: python,dictionary,copy-on-write,cow
Platform: UNKNOWN
Classifier: Development Status :: 5 - Production/Stable
Classifier: Intended Audience :: Developers
Classifier: License :: OSI Approved :: GNU Affero General Public License v3 or later (AGPLv3+)
Classifier: Programming Language :: Python :: 3
Classifier: Programming Language :: Python :: 3.4
Classifier: Programming Language :: Python :: 3.5
Classifier: Programming Language :: Python :: 3.6
Classifier: Topic :: Software Development :: Libraries :: Python Modules
